pokespeed/__coconut__.py
pokespeed/__init__.py
pokespeed/__main__.py
pokespeed-1.1.1.dist-info/LICENSE
pokespeed-1.1.1.dist-info/METADATA
pokespeed-1.1.1.dist-info/WHEEL
pokespeed-1.1.1.dist-info/entry_points.txt
pokespeed-1.1.1.dist-info/top_level.txt
pokespeed-1.1.1.dist-info/RECORD
