Metadata-Version: 2.1
Name: pokespeed
Version: 1.1.1
Summary: Calculate Pokemon speed tiers.
Home-page: https://github.com/evhub/pokespeed
Author: Evan Hubinger
License-File: LICENSE
Requires-Dist: requests
Requires-Dist: pypokedex
Requires-Dist: beautifulsoup4
Requires-Dist: tqdm
Requires-Dist: clize
